evergy/__init__.py
evergy/evergy.py
evergy/utils.py
evergy-2.0.4.dist-info/LICENSE
evergy-2.0.4.dist-info/METADATA
evergy-2.0.4.dist-info/WHEEL
evergy-2.0.4.dist-info/top_level.txt
evergy-2.0.4.dist-info/RECORD
