Metadata-Version: 2.1
Name: evergy
Version: 2.0.4
Summary: A utility that reads electric utility meter data from Evergy.com
Home-page: https://github.com/lawrencefoley/evergy
Author: Lawrence Foley
Author-email: lawrencefoley@live.com
License: UNKNOWN
Project-URL: Documentation, https://evergy.readthedocs.io/en/latest/
Project-URL: Source, https://github.com/lawrencefoley/evergy/
Project-URL: Tracker, https://github.com/lawrencefoley/evergy/issues
Project-URL: Maintainer, https://lawrencefoley.com
Keywords: evergy kcpl kansas-city electricity-consumption electricity-meter api
Platform: UNKNOWN
Classifier: Development Status :: 4 - Beta
Classifier: Intended Audience :: Developers
Classifier: Topic :: Utilities
Classifier: License :: OSI Approved :: MIT License
Classifier: Programming Language :: Python :: 3.9
Classifier: Programming Language :: Python :: 3.10
Requires-Python: >=3
License-File: LICENSE
Requires-Dist: beautifulsoup4 (==4.10.0)
Requires-Dist: requests (==2.26.0)
